URLDecoder/__init__.py
URLDecoder/decoder.py
URLDecoder/demo.py
URLDecoder-1.0.3.dist-info/LICENSE
URLDecoder-1.0.3.dist-info/METADATA
URLDecoder-1.0.3.dist-info/WHEEL
URLDecoder-1.0.3.dist-info/top_level.txt
URLDecoder-1.0.3.dist-info/RECORD
