Metadata-Version: 2.1
Name: URLDecoder
Version: 1.0.3
Summary: A simple URL decoder that converts URL-encoded strings to JSON objects
Home-page: https://github.com/Evil0ctal/URLDecoder
Author: Evil0ctal
Author-email: evil0ctal1985@gmail.com
License: MIT
Keywords: encoded url decoder json
License-File: LICENSE
